f_it/__init__.py
f_it/fit.py
f_it/utils.py
f_it/version.py
f_it-0.6.1.dist-info/LICENSE
f_it-0.6.1.dist-info/METADATA
f_it-0.6.1.dist-info/WHEEL
f_it-0.6.1.dist-info/top_level.txt
f_it-0.6.1.dist-info/RECORD
