Metadata-Version: 2.1
Name: f-it
Version: 0.6.1
Summary: UNKNOWN
Home-page: https://github.com/clbarnes/f_it
Author: Chris L. Barnes
License: UNKNOWN
Platform: UNKNOWN
Classifier: Development Status :: 3 - Alpha
Classifier: License :: OSI Approved :: MIT License
Classifier: Programming Language :: Python :: 3
Classifier: Programming Language :: Python :: 3.7
Classifier: Programming Language :: Python :: 3.8
Classifier: Programming Language :: Python :: 3.9
Requires-Python: >=3.7, <4.0
Provides-Extra: all
Requires-Dist: tqdm ; extra == 'all'
Provides-Extra: progress
Requires-Dist: tqdm ; extra == 'progress'
